pyfinance_tunisia.py
pyfinance_tunisia-0.0.9.dist-info/LICENSE
pyfinance_tunisia-0.0.9.dist-info/METADATA
pyfinance_tunisia-0.0.9.dist-info/WHEEL
pyfinance_tunisia-0.0.9.dist-info/top_level.txt
pyfinance_tunisia-0.0.9.dist-info/RECORD
